{
    "area":  "gineco_obstetricia",
    "dominio":  "cancer_ginecologico",
    "total":  48,
    "cards":  [
                  {
                      "l":  "F1",
                      "f":  "Qual o tipo histológico mais comum do câncer de colo uterino?",
                      "v":  "Carcinoma de células escamosas (epidermoide), responsável por cerca de 70-80% dos casos. O segundo mais comum é o adenocarcinoma."
                  },
                  {
                      "l":  "F1",
                      "f":  "Qual o principal agente etiológico do câncer de colo do útero?",
                      "v":  "Infecção persistente pelo HPV (Papilomavírus Humano) de alto risco oncogênico, principalmente os subtipos 16 e 18."
                  },
                  {
                      "l":  "F1",
                      "f":  "Defina NIC (Neoplasia Intraepitelial Cervical) e suas classificações.",
                      "v":  "Lesão precursora do câncer de colo uterino. NIC I (displasia leve, terço inferior do epitélio), NIC II (displasia moderada, até 2/3), NIC III (displasia grave/carcinoma in situ, mais de 2/3 ou toda espessura)."
                  },
                  {
                      "l":  "F1",
                      "f":  "Qual o sistema de estadiamento utilizado para o câncer de colo do útero?",
                      "v":  "Estadiamento FIGO, que tradicionalmente era clínico, mas desde a revisão de 2018 permite uso de exames de imagem e achados anatomopatológicos."
                  },
                  {
                      "l":  "F1",
                      "f":  "Qual o tipo histológico mais comum do câncer de endométrio?",
                      "v":  "Adenocarcinoma endometrioide, correspondendo ao tipo I (estrogênio-dependente), responsável por cerca de 80% dos casos."
                  },
                  {
                      "l":  "F1",
                      "f":  "Qual o principal fator de risco para o câncer de endométrio?",
                      "v":  "Exposição estrogênica sem oposição da progesterona (hiperestrogenismo), associado a obesidade, nuliparidade, menarca precoce, menopausa tardia, SOP e uso de tamoxifeno."
                  },
                  {
                      "l":  "F1",
                      "f":  "O que é hiperplasia endometrial atípica?",
                      "v":  "Proliferação glandular endometrial com atipias celulares, considerada lesão precursora do adenocarcinoma de endométrio, com risco de progressão ou coexistência com carcinoma em cerca de 25-40%."
                  },
                  {
                      "l":  "F1",
                      "f":  "Qual o tipo histológico mais comum do câncer de ovário?",
                      "v":  "Tumores epiteliais, sendo o adenocarcinoma seroso de alto grau o subtipo mais frequente dos cânceres ovarianos malignos."
                  },
                  {
                      "l":  "F1",
                      "f":  "Qual marcador tumoral é mais associado ao câncer epitelial de ovário?",
                      "v":  "CA-125, útil no acompanhamento e avaliação de massas anexiais em mulheres na pós-menopausa (não é específico nem indicado para rastreamento)."
                  },
                  {
                      "l":  "F1",
                      "f":  "Qual o tipo histológico mais comum do câncer de vulva?",
                      "v":  "Carcinoma de células escamosas (epidermoide), responsável por cerca de 90% dos casos."
                  },
                  {
                      "l":  "F1",
                      "f":  "Defina doença trofoblástica gestacional e suas formas.",
                      "v":  "Espectro de proliferações trofoblásticas anormais. Inclui formas benignas (mola hidatiforme completa e parcial) e malignas (mola invasora, coriocarcinoma, tumor trofoblástico do sítio placentário)."
                  },
                  {
                      "l":  "F1",
                      "f":  "Qual marcador é fundamental no diagnóstico e seguimento da neoplasia trofoblástica gestacional?",
                      "v":  "Beta-hCG (gonadotrofina coriônica humana), cujos níveis quantitativos são usados para diagnóstico, monitoramento da resposta terapêutica e detecção de recidiva."
                  },
                  {
                      "l":  "F2",
                      "f":  "Qual a diferença entre os tipos histológicos I e II do câncer de endométrio?",
                      "v":  "Tipo I (endometrioide): estrogênio-dependente, bom prognóstico, associado a hiperplasia, obesidade e nuliparidade, expressa receptor hormonal. Tipo II (seroso/células claras): não estrogênio-dependente, agressivo, ocorre em endométrio atrófico, associado à mutação de p53, pior prognóstico."
                  },
                  {
                      "l":  "F2",
                      "f":  "Como distinguir lesão intraepitelial cervical de baixo grau (LSIL) de alto grau (HSIL)?",
                      "v":  "LSIL (NIC I): displasia leve, comprometimento de até 1/3 do epitélio, alta taxa de regressão espontânea, conduta expectante. HSIL (NIC II/III): displasia moderada/grave, acomete 2/3 ou todo o epitélio, maior risco de progressão para câncer, requer tratamento (EZT/conização)."
                  },
                  {
                      "l":  "F2",
                      "f":  "Qual a diferença entre HPV de baixo e alto risco oncogênico?",
                      "v":  "Baixo risco (6 e 11): causam verrugas genitais (condilomas), raramente associados a câncer. Alto risco (16 e 18, principalmente): responsáveis por ~70% dos cânceres de colo uterino; integram seu DNA ao genoma da célula hospedeira e inativam p53 (E6) e Rb (E7)."
                  },
                  {
                      "l":  "F2",
                      "f":  "Como diferenciar câncer de colo uterino de tipo escamoso vs adenocarcinoma?",
                      "v":  "Carcinoma escamoso: ~80-90% dos casos, origem na zona de transformação, mais detectável pela citologia. Adenocarcinoma: ~10-20%, origina-se do epitélio glandular endocervical, mais difícil de rastrear, geralmente diagnóstico mais tardio e pior prognóstico relativo."
                  },
                  {
                      "l":  "F2",
                      "f":  "Qual a diferença entre tumor de ovário epitelial, germinativo e estromal?",
                      "v":  "Epitelial: mais comum (~90%), acomete mulheres pós-menopausa, deriva do epitélio celômico. Germinativo: jovens (\u003c30 anos), origina das células germinativas (ex: disgerminoma, teratoma). Estromal/cordões sexuais: produzem hormônios (ex: granulosa-estrogênio, Sertoli-Leydig-androgênio)."
                  },
                  {
                      "l":  "F2",
                      "f":  "Como distinguir mola hidatiforme completa de parcial?",
                      "v":  "Completa: cariótipo 46XX (diploide, origem paterna), ausência de feto, vilosidades todas hidrópicas, β-hCG muito elevado, maior risco de malignização (~20%). Parcial: triploide (69XXY), presença de feto/tecido fetal, vilosidades focais, β-hCG menos elevado, menor risco de malignização (~5%)."
                  },
                  {
                      "l":  "F2",
                      "f":  "Qual a diferença entre os marcadores CA-125, CEA e CA 19-9 nos tumores ovarianos?",
                      "v":  "CA-125: principal marcador de tumores epiteliais (especialmente seroso); pouco específico. CEA e CA 19-9: elevam-se em tumores mucinosos do ovário; CEA também sugere origem metastática (gastrointestinal). Razão CEA/CA-125 ajuda a diferenciar primário ovariano de metástase."
                  },
                  {
                      "l":  "F2",
                      "f":  "Como distinguir hiperplasia endometrial com atipia de sem atipia?",
                      "v":  "Sem atipia: baixo risco de progressão (~1-3%), tratamento hormonal (progestágeno). Com atipia (neoplasia intraepitelial endometrial): alto risco de progressão para adenocarcinoma (~25-40%) e até 40% já têm carcinoma associado; conduta preferencial é histerectomia."
                  },
                  {
                      "l":  "F2",
                      "f":  "Qual a diferença entre os marcadores AFP, β-hCG e LDH nos tumores germinativos de ovário?",
                      "v":  "AFP: elevada no tumor do seio endodérmico (saco vitelínico) e carcinoma embrionário. β-hCG: elevado em coriocarcinoma e disgerminoma (eventualmente). LDH: marcador do disgerminoma. Teratoma maduro geralmente não eleva marcadores."
                  },
                  {
                      "l":  "F2",
                      "f":  "Quando indicar conização vs histerectomia no manejo de lesões cervicais?",
                      "v":  "Conização (EZT): indicada em HSIL, com finalidade diagnóstica e terapêutica, preserva fertilidade. Histerectomia: reservada para casos de carcinoma invasor (após estadiamento), margem comprometida sem possibilidade de nova conização, prole completa ou patologias uterinas associadas."
                  },
                  {
                      "l":  "F2",
                      "f":  "Como diferenciar o sangramento da neoplasia trofoblástica gestacional do aborto?",
                      "v":  "NTG/mola: útero maior que o esperado para idade gestacional, β-hCG muito elevado, hiperêmese, eliminação de vesículas, ausência de BCF, cistos teca-luteínicos. Aborto: útero compatível ou menor, β-hCG em queda, restos ovulares na USG."
                  },
                  {
                      "l":  "F2",
                      "f":  "Qual a diferença entre câncer de vulva e líquen escleroso quanto ao risco?",
                      "v":  "Líquen escleroso: dermatose crônica vulvar, prurido intenso, pele com aspecto de papel de cigarro, é fator de risco para carcinoma de vulva (transformação em ~4-5% dos casos). Câncer de vulva: lesão ulcerada/nodular persistente, exige biópsia; tipo mais comum é o carcinoma escamoso."
                  },
                  {
                      "l":  "F3",
                      "f":  "Qual a conduta diante de citologia (Papanicolau) com resultado ASC-US em mulher de 30 anos?",
                      "v":  "Repetir citologia em 6 meses. Se nova alteração (≥ASC-US), encaminhar para colposcopia. Alternativa: teste de DNA-HPV; se positivo, colposcopia. Em mulheres ≥30 anos pode-se priorizar o teste de HPV."
                  },
                  {
                      "l":  "F3",
                      "f":  "Qual a conduta na citologia com lesão intraepitelial de alto grau (HSIL)?",
                      "v":  "Encaminhar imediatamente para colposcopia. Se achados maiores, fazer biópsia ou diretamente excisão (ver e tratar com EZT/conização). NIC 2/3 confirmado → tratamento excisional (CAF/conização)."
                  },
                  {
                      "l":  "F3",
                      "f":  "Como rastrear o câncer de colo uterino no Brasil (Ministério da Saúde)?",
                      "v":  "Citologia oncótica em mulheres de 25 a 64 anos que já iniciaram atividade sexual. Os 2 primeiros exames com intervalo anual; se ambos normais, repetir a cada 3 anos."
                  },
                  {
                      "l":  "F3",
                      "f":  "Qual o tratamento do câncer de colo uterino estádio IA1 (invasão ≤3mm) sem invasão linfovascular?",
                      "v":  "Conização com margens livres (se deseja preservar fertilidade) ou histerectomia simples (tipo A). Não requer linfadenectomia. Prognóstico excelente."
                  },
                  {
                      "l":  "F3",
                      "f":  "Qual o tratamento padrão para câncer de colo uterino estádio IB2/IIA (tumor volumoso ou avançado localmente)?",
                      "v":  "A partir de estádio IB3/IIB: quimiorradioterapia concomitante (cisplatina semanal + radioterapia externa + braquiterapia). Cirurgia (Wertheim-Meigs) reservada para tumores iniciais (até IB2/IIA1)."
                  },
                  {
                      "l":  "F3",
                      "f":  "Qual o exame de escolha e a conduta inicial no sangramento uterino pós-menopausa?",
                      "v":  "Ultrassonografia transvaginal. Endométrio \u003e4-5mm ou sangramento persistente → biópsia endometrial/histeroscopia com biópsia. Sangramento pós-menopausa é câncer de endométrio até prova em contrário."
                  },
                  {
                      "l":  "F3",
                      "f":  "Qual o tratamento padrão do câncer de endométrio estádio I?",
                      "v":  "Histerectomia total com salpingo-ooforectomia bilateral + avaliação/linfadenectomia (estadiamento cirúrgico). Radioterapia adjuvante conforme fatores de risco (grau, invasão miometrial)."
                  },
                  {
                      "l":  "F3",
                      "f":  "Qual o marcador tumoral e a tríade clínica suspeita de câncer de ovário epitelial?",
                      "v":  "CA-125 (epitelial seroso). Quadro: massa anexial sólida/complexa + ascite + distensão abdominal em mulher pós-menopausa. Avaliar índice de risco de malignidade (RMI)."
                  },
                  {
                      "l":  "F3",
                      "f":  "Qual a conduta cirúrgica padrão no câncer de ovário epitelial avançado?",
                      "v":  "Citorredução cirúrgica máxima (debulking) com objetivo de doença residual zero, seguida de quimioterapia adjuvante com carboplatina + paclitaxel. Estadiamento é cirúrgico."
                  },
                  {
                      "l":  "F3",
                      "f":  "Quais os red flags de uma massa anexial sugestivos de malignidade?",
                      "v":  "Componente sólido, septos espessos, projeções papilares, vascularização central ao Doppler, ascite, bilateralidade, tamanho \u003e10cm, pós-menopausa, CA-125 elevado e crescimento rápido."
                  },
                  {
                      "l":  "F3",
                      "f":  "Qual a conduta na mola hidatiforme completa após esvaziamento uterino?",
                      "v":  "Esvaziamento por vácuo-aspiração + seguimento com beta-hCG semanal até negativação por 3 semanas, depois mensal por 6 meses. Contracepção eficaz no período. Vigiar neoplasia trofoblástica gestacional."
                  },
                  {
                      "l":  "F3",
                      "f":  "Como conduzir o diagnóstico de neoplasia trofoblástica gestacional pós-molar?",
                      "v":  "Suspeitar se beta-hCG em platô (4 valores em 3 semanas), elevação (3 valores em 2 semanas) ou persistência após 6 meses. Estadiar (FIGO/OMS) e tratar com quimioterapia: metotrexato (baixo risco) ou EMA-CO (alto risco)."
                  },
                  {
                      "l":  "F4",
                      "f":  "Por que a infecção persistente pelo HPV de alto risco (16/18) leva à carcinogênese cervical? Explique o mecanismo molecular.",
                      "v":  "As oncoproteínas virais E6 e E7 são os principais agentes transformadores. E6 promove degradação do p53 (via ubiquitina-ligase E6-AP), bloqueando apoptose e reparo do DNA. E7 inativa a proteína do retinoblastoma (pRb), liberando o fator E2F e permitindo progressão descontrolada do ciclo celular (G1→S). A perda combinada desses freios tumorais, somada à integração viral ao genoma do hospedeiro, acumula mutações e instabilidade genômica, evoluindo de NIC para carcinoma invasor ao longo de anos."
                  },
                  {
                      "l":  "F4",
                      "f":  "Como o subtipo histológico do câncer de endométrio (Tipo I vs Tipo II) se relaciona com a fisiopatologia, fatores de risco e prognóstico?",
                      "v":  "Tipo I (endometrioide, ~80%): estrogênio-dependente, surge de hiperplasia endometrial atípica, associado a obesidade, SOP, anovulação, tamoxifeno, nuliparidade; expressa receptores hormonais, baixo grau, bom prognóstico; mutações em PTEN, KRAS, instabilidade de microssatélites. Tipo II (seroso, células claras): estrogênio-independente, surge de endométrio atrófico em mulheres mais velhas, alto grau, agressivo, pior prognóstico; mutação em p53. Essa distinção orienta estadiamento e necessidade de tratamento adjuvante."
                  },
                  {
                      "l":  "F4",
                      "f":  "Integre os conceitos de Síndrome de Lynch no risco de cânceres ginecológicos: quais tumores e qual conduta de rastreamento?",
                      "v":  "A Síndrome de Lynch (mutação em genes de reparo MMR: MLH1, MSH2, MSH6, PMS2) confere risco elevado de câncer colorretal, mas o câncer de endométrio é frequentemente a neoplasia sentinela na mulher (risco de até 40-60%), além de risco aumentado de câncer de ovário. Conduta: rastreamento endometrial anual (USG transvaginal + biópsia endometrial) a partir dos 30-35 anos e consideração de histerectomia + salpingo-ooforectomia profilática após prole completa. Tumores apresentam instabilidade de microssatélites."
                  },
                  {
                      "l":  "F4",
                      "f":  "Por que a salpingo-ooforectomia bilateral redutora de risco é indicada em portadoras de mutação BRCA, e qual a base fisiopatológica do câncer de ovário seroso de alto grau?",
                      "v":  "Mutações em BRCA1/2 comprometem o reparo do DNA por recombinação homóloga, elevando o risco de câncer de mama e ovário. Evidências mostram que a maioria dos carcinomas serosos de alto grau de ovário origina-se das fímbrias tubárias (lesão precursora STIC – carcinoma intraepitelial seroso tubário), não do epitélio ovariano. Por isso, recomenda-se salpingo-ooforectomia bilateral entre 35-40 anos (BRCA1) e 40-45 anos (BRCA2) após prole completa, reduzindo drasticamente o risco. O defeito de reparo também justifica a sensibilidade a inibidores de PARP."
                  },
                  {
                      "l":  "F4",
                      "f":  "Como a doença trofoblástica gestacional se relaciona com a origem genética e o risco de transformação maligna (mola completa vs parcial)?",
                      "v":  "Mola completa: cariótipo diploide (46,XX) de origem totalmente paterna (fertilização de óvulo sem material genético materno), sem tecido fetal, vilosidades hidrópicas difusas, hCG muito elevado, risco de progressão para neoplasia trofoblástica em ~15-20%. Mola parcial: triploide (69,XXY) com material materno e paterno, presença de tecido fetal anômalo, vilosidades focais, hCG menos elevado, risco de malignização baixo (~1-5%). O seguimento com hCG seriado é essencial para detectar neoplasia trofoblástica gestacional precoce."
                  },
                  {
                      "l":  "F4",
                      "f":  "Qual o mecanismo de ação dos inibidores de PARP (olaparibe) no câncer de ovário e por que são especialmente eficazes em tumores BRCA-mutados?",
                      "v":  "A PARP repara quebras de fita simples do DNA. Sua inibição leva ao acúmulo dessas lesões, que se convertem em quebras de dupla fita durante a replicação. Em células normais, a recombinação homóloga (dependente de BRCA) repara esses danos. Em tumores BRCA-mutados, essa via está deficiente, criando \u0027letalidade sintética\u0027: a célula tumoral não consegue reparar o DNA e morre, enquanto células normais sobrevivem. Por isso, inibidores de PARP são eficazes na manutenção de câncer de ovário com deficiência de recombinação homóloga (HRD)."
                  },
                  {
                      "l":  "F4",
                      "f":  "Integre os conceitos de marcadores tumorais (CA-125, CEA, beta-hCG, AFP, LDH, inibina) no diagnóstico diferencial das massas anexiais.",
                      "v":  "CA-125: elevado em tumores epiteliais serosos (também em endometriose, DIP, gravidez). CEA: associado a tumores mucinosos e metástases gastrointestinais (Krukenberg). Beta-hCG e AFP: marcadores de tumores de células germinativas (coriocarcinoma, tumor do seio endodérmico/saco vitelino). LDH e beta-hCG: disgerminoma. Inibina e AFP/estrogênio: tumores dos cordões sexuais-estroma (granulosa produz inibina e estrogênio; Sertoli-Leydig produz androgênios). O índice de risco de malignidade (RMI) combina CA-125, USG e status menopausal."
                  },
                  {
                      "l":  "F4",
                      "f":  "Por que mulheres com câncer de células da granulosa devem ser investigadas para hiperplasia/câncer de endométrio, e qual o mecanismo?",
                      "v":  "Os tumores de células da granulosa secretam estrogênio de forma autônoma e contínua, sem oposição progestínica. Esse hiperestrogenismo crônico estimula a proliferação endometrial, causando hiperplasia endometrial (em até 25-50% dos casos) e câncer de endométrio concomitante (em ~5-10%). Clinicamente manifestam-se por sangramento uterino anormal, pseudopuberdade precoce em crianças ou sangramento pós-menopausa. Por isso, a investigação endometrial (biópsia/curetagem) é mandatória ao diagnóstico desses tumores. A inibina é marcador útil para seguimento."
                  },
                  {
                      "l":  "F4",
                      "f":  "Como o estadiamento do câncer de colo uterino é definido e por que ele é predominantemente clínico (FIGO)? Conecte com as implicações terapêuticas.",
                      "v":  "Tradicionalmente o estadiamento FIGO do colo é clínico (exame físico, especular, toque retal/vaginal), pois grande parte dos casos ocorre em países com acesso limitado a imagem. A FIGO 2018 passou a incorporar imagem (RM, TC, PET) e achados patológicos (status linfonodal). A profundidade de invasão, extensão paramétrica e acometimento linfonodal determinam a conduta: estágios iniciais (IA-IB1) — cirurgia (histerectomia radical de Wertheim-Meigs + linfadenectomia); estágios avançados (IB3 em diante / paramétrios) — quimiorradioterapia concomitante com cisplatina (radiossensibilizante) + braquiterapia."
                  },
                  {
                      "l":  "F4",
                      "f":  "Por que a citorredução cirúrgica ótima é determinante prognóstico no câncer de ovário avançado, e como se relaciona com a quimioterapia?",
                      "v":  "O câncer de ovário epitelial dissemina-se precocemente pela cavidade peritoneal (carcinomatose). A citorredução ótima — definida como ausência de doença residual macroscópica (R0) ou implantes \u003c1 cm — é o fator prognóstico modificável mais importante, pois reduz a massa tumoral, melhora a perfusão e a entrega da quimioterapia aos focos remanescentes e diminui células quimiorresistentes. Combina-se com quimioterapia adjuvante baseada em platina + taxano (carboplatina + paclitaxel). Em casos irressecáveis inicialmente, opta-se por quimioterapia neoadjuvante seguida de cirurgia de intervalo."
                  },
                  {
                      "l":  "F4",
                      "f":  "Integre os fatores de risco e fisiopatologia que conectam obesidade, resistência insulínica e câncer de endométrio.",
                      "v":  "Na obesidade, o tecido adiposo converte androgênios em estrogênio via aromatase periférica, gerando hiperestrogenismo sem oposição progestínica (sobretudo na pós-menopausa). A resistência insulínica eleva a insulina e o IGF-1, que têm efeito mitogênico direto sobre o endométrio e reduzem a SHBG, aumentando a fração de estrogênio livre. A SOP agrava esse quadro pela anovulação crônica (ausência de progesterona). O resultado é estímulo proliferativo endometrial persistente → hiperplasia → adenocarcinoma endometrioide (Tipo I). Por isso obesidade, diabetes, SOP e nuliparidade são fatores de risco interligados."
                  },
                  {
                      "l":  "F4",
                      "f":  "Como diferenciar e integrar o manejo das neoplasias intraepiteliais escamosas (LSIL/HSIL) na conduta do rastreamento e tratamento do câncer de colo?",
                      "v":  "LSIL (NIC 1) reflete infecção produtiva pelo HPV, com alto índice de regressão espontânea (~60-70%), conduta geralmente expectante com seguimento citológico/colposcópico, especialmente em jovens. HSIL (NIC 2/3) representa lesão precursora verdadeira com risco real de progressão para carcinoma invasor, exigindo tratamento excisional (EZT/conização com CAF) ou destrutivo. A colposcopia com biópsia confirma o grau histológico. A integração rastreamento (citologia/teste de HPV) → colposcopia → biópsia → tratamento conforme grau é a base da prevenção secundária, complementada pela vacinação (prevenção primária)."
                  }
              ]
}