{
    "area":  "cirurgia_geral",
    "dominio":  "hernias_parede_abdominal",
    "quiz":  "quiz_002",
    "total":  50,
    "questions":  [
                      {
                          "q":  "Um paciente apresenta hérnia inguinal com saco herniário que passa pela lateral do cordão espermático. Qual é a classificação dessa hérnia segundo o triângulo de Hasselbach?",
                          "opts":  [
                                       "Escrotal",
                                       "Indireta",
                                       "Direta",
                                       "Femoral"
                                   ],
                          "c":  1,
                          "exp":  "Hérnia indireta passa LATERAL (fora) do triângulo de Hasselbach, percorrendo o anel inguinal interno através do cordão espermático."
                      },
                      {
                          "q":  "Uma criança de 3 anos apresenta abaulamento no umbigo que desaparece quando a criança está deitada. Qual é o manejo mais apropriado nessa idade?",
                          "opts":  [
                                       "Cirurgia imediata",
                                       "Observação clínica até 4-5 anos",
                                       "Faixa elástica permanente",
                                       "Injeção percutânea de esclerosante"
                                   ],
                          "c":  1,
                          "exp":  "Hérnias umbilicais em crianças fecham espontaneamente até 4-5 anos. Conduta expectante é padrão-ouro, não requer intervenção precoce."
                      },
                      {
                          "q":  "Um homem de 55 anos com hérnia femoral bilateral apresenta dor súbita e vômitos há 2 horas. O abdome está tenso e reduzível. Qual termo descreve o quadro clínico?",
                          "opts":  [
                                       "Hérnia encarcerada",
                                       "Hérnia adquirida",
                                       "Hérnia redutível",
                                       "Hérnia estrangulada"
                                   ],
                          "c":  3,
                          "exp":  "Estrangulamento = encarceramento COM compromisso vascular (isquemia tissular), evidenciado por dor aguda, vômitos e sinais peritoneal."
                      },
                      {
                          "q":  "Na técnica de Lichtenstein para herniorrafia inguinal, qual estrutura anatômica é essencial para o posicionamento correto da tela de polipropileno?",
                          "opts":  [
                                       "Vasos epigástricos inferiores",
                                       "Periósteo do púbis",
                                       "Ligamento inguinal",
                                       "Ligamento de Cooper"
                                   ],
                          "c":  2,
                          "exp":  "Ligamento inguinal é ponto de referência para fixação infralateral da tela, reduzindo risco de recorrência medial e garantindo anatomia funcional."
                      },
                      {
                          "q":  "Uma mulher apresenta abaulamento doloroso na parede abdominal lateral, 2 cm acima e medial à espinha ilíaca anterossuperior. Qual hérnia é mais provável?",
                          "opts":  [
                                       "Hérnia de Grynfelt",
                                       "Hérnia de Spiegel",
                                       "Hérnia de Richter",
                                       "Hérnia obturatória"
                                   ],
                          "c":  1,
                          "exp":  "Hérnia de Spiegel hernia através da fáscia de Spiegel (linha semilunar), tipicamente localizada acima linha semicircular (linea arcuata)."
                      },
                      {
                          "q":  "Um paciente submetido a cirurgia de apendicectomia há 1 mês retorna com abaulamento na incisão que aumenta ao tossir. Qual termo define essa complicação?",
                          "opts":  [
                                       "Eventração incompleta",
                                       "Deiscência de ferida",
                                       "Hérnia incisional",
                                       "Seroma incisional"
                                   ],
                          "c":  2,
                          "exp":  "Hérnia incisional é protrusão de vísceras através de defeito na cicatriz cirúrgica prévia, aumenta com Valsalva ou Tosse."
                      },
                      {
                          "q":  "Qual região anatômica delimita o triângulo de Hasselbach medialmente, sendo importante para diferencial entre hérnias inguinais diretas e indiretas?",
                          "opts":  [
                                       "Fáscia transversa",
                                       "Cordão espermático",
                                       "Artéria epigástrica inferior",
                                       "Ligamento de Cooper"
                                   ],
                          "c":  2,
                          "exp":  "Artéria epigástrica inferior é limite MEDIAL do triângulo de Hasselbach. Hérnia direta ocorre MEDIAL a ela, na parede posterior fraca."
                      },
                      {
                          "q":  "Uma mulher de 62 anos com obesidade apresenta dor na região inguinal alta, mas exame físico inguinal normal. Ressonância mostra pequeno saco herniário femoral. Qual é a localização exata dessa hérnia?",
                          "opts":  [
                                       "Através do canal obturador",
                                       "Medial ao ligamento inguinal e medial à veia femoral",
                                       "Lateral ao ligamento inguinal e lateral à artéria femoral",
                                       "Medial ao ligamento de Cooper"
                                   ],
                          "c":  1,
                          "exp":  "Hérnia femoral passa MEDIAL à veia femoral, INFERIOR ao ligamento inguinal, através espaço de Gimbernat (canal femoral)."
                      },
                      {
                          "q":  "Um adulto com hérnia umbilical de 3 cm apresenta sintomas de irredutibilidade. Qual é a indicação de tratamento?",
                          "opts":  [
                                       "Apenas se complicada com estrangulamento",
                                       "Apenas se \u003e 2 cm de diâmetro",
                                       "Sempre que estiver irredutível ou sintomática",
                                       "Após 10 anos de observação"
                                   ],
                          "c":  2,
                          "exp":  "Hérnias umbilicais de adulto com irredutibilidade ou sintomas (dor, desconforto) requerem reparo cirúrgico para evitar encarceramento."
                      },
                      {
                          "q":  "Uma hérnia inguinal em que o saco atravessa o anel inguinal profundo mas permanece medial aos vasos epigástricos inferiores pertence a qual classificação de Nyhus?",
                          "opts":  [
                                       "Tipo III",
                                       "Tipo I",
                                       "Tipo II",
                                       "Tipo IV"
                                   ],
                          "c":  2,
                          "exp":  "Nyhus Tipo II = hérnia inguinal primária direta com anel inguinal interno normal. Saco passa medial aos vasos epigástricos inferiores."
                      },
                      {
                          "q":  "Homem 45 anos com hérnia inguinal direita recorrente 3 anos após herniorrafia anterior. Ao exame físico, confirma-se hérnia redutível na região medial ao ligamento inguinal lateral. Qual é o mecanismo fisiopatológico mais provável desta recorrência?",
                          "opts":  [
                                       "Deiscência completa da sutura na técnica de Bassini com necrose tecidual",
                                       "Enfraquecimento da parede posterior do canal inguinal (assoalho) por lesão do ligamento de Cooper",
                                       "Progressão natural da hérnia indireta para localização direta após 3 anos",
                                       "Falha na identificação de saco herniário indireto residual durante operação prévia"
                                   ],
                          "c":  1,
                          "exp":  "Hérnias inguinais diretas recorrentes ocorrem por enfraquecimento do assoalho do canal inguinal, especialmente se ligamento de Cooper foi danificado ou não adequadamente reforçado."
                      },
                      {
                          "q":  "Mulher 38 anos com tumoração indolor na região supra-medial da coxa, próxima ao ligamento inguinal. O teste de redução revela protuberância que persiste mesmo com pressão intra-abdominal (sem tossir). Qual achado clínico diferencia esta hérnia femoral de uma inguinal?",
                          "opts":  [
                                       "Localização abaixo e lateral ao ligamento inguinal",
                                       "Consistência mais fixa e menor redutibilidade",
                                       "Ausência de impulso ao aumento de pressão abdominal",
                                       "Comprimento maior da estrutura palpável ao exame"
                                   ],
                          "c":  0,
                          "exp":  "Hérnia femoral situa-se abaixo e lateral ao ligamento inguinal, passando através do triângulo de Cloquet (entre ligamento lacunar e ligamento pectíneo), diferenciando-se de inguinal."
                      },
                      {
                          "q":  "Lactente 8 meses com protuberância umbilical que desaparece completamente ao deitar-se com abdômen relaxado. Pai relata nota-se mais evidente ao chorar. Qual é o manejo mais apropriado nesta idade?",
                          "opts":  [
                                       "Herniorrafia eletiva com malha aos 10 meses de vida",
                                       "Encaminhamento cirúrgico urgente para evitar encarceramento",
                                       "Observação clínica até 4-5 anos, pois a maioria fecha espontaneamente",
                                       "Aplicação de adesivos e contenção elástica contínua"
                                   ],
                          "c":  2,
                          "exp":  "Hérnias umbilicais em menores de 5 anos têm alta taxa de fechamento espontâneo (até 90%) devido à maturação muscular e aumento da pressão abdominal com crescimento; observação é conduta-padrão."
                      },
                      {
                          "q":  "Paciente 62 anos apresenta dor súbita em região inguinal esquerda com tumoração firme, irredutível há 6 horas, acompanhada de náuseas. À ausculta, ausência de peristaltismo. Qual complicação herniária é mais provável?",
                          "opts":  [
                                       "Hérnia incarcerante com aderências densas mas sem isquemia",
                                       "Estrangulamento com comprometimento vascular e necessidade de redução urgente",
                                       "Encarceramento crônico com peritonite lentamente progressiva",
                                       "Encarceramento sem isquemia, com redução possível após sedação"
                                   ],
                          "c":  1,
                          "exp":  "Irredutibilidade súbita + dor intensa + náuseas + ausência de peristaltismo sugerem estrangulamento com obstrução e isquemia, diferenciando de encarceramento (pode ser reduzido com sedação e sem sinais sistêmicos)."
                      },
                      {
                          "q":  "Homem 52 anos foi submetido a herniorrafia inguinal esquerda por técnica de Lichtenstein há 2 anos. Apresenta agora dor crônica na região operada (neuralgia pós-operatória) sem recorrência herniária. Qual estrutura neurológica é classicamente envolvida nesta complicação?",
                          "opts":  [
                                       "Nervo ilioinguinal por trauma ou aprisionamento durante dissecção ou fixação de malha",
                                       "Nervo genitofemoral por isquemia durante sutura de Cooper",
                                       "Nervo iliohipogástrico por colocação profunda de malha",
                                       "Nervo cutâneo femoral lateral por erosão de malha em região pubiana"
                                   ],
                          "c":  0,
                          "exp":  "O nervo ilioinguinal é estrutura de superfície no canal inguinal e é frequentemente traumatizado ou aprisionado por sutura durante herniorrafia convencional; lesão causa dor crônica e parestesias típicas."
                      },
                      {
                          "q":  "Paciente 70 anos com hérnia incisional ampla (12 cm) em cicatriz de laparotomia mediana prévia. Ultrassom mostra defasciamento importante com conteúdo hepático. Qual técnica de repair traz melhor relação risco-benefício considerando idade e comorbidades?",
                          "opts":  [
                                       "Observação conservadora com faixa abdominal, evitando risco cirúrgico",
                                       "Técnica completamente laparoscópica com malha intraperitoneal",
                                       "Herniorrafia primária com sutura de fascia somente (Bassini-adaptado)",
                                       "Colocação de malha em posição retrorreta com reforço de fascia"
                                   ],
                          "c":  3,
                          "exp":  "Posição retrorreta em hérnias incisionais amplas oferece menor taxa de recorrência, menor contato malha-viscera, boa vascularização e menor morbidade que laparoscopia pura em idosos com comorbidades."
                      },
                      {
                          "q":  "Mulher 48 anos relata sensação de protuberância dolorosa no flanco anterolateral direito, abaixo do ponto de intersecção da linha semilunar com a linha arqueada (Douglas). Supeita-se hérnia de Spiegel. Qual estrutura anatômica representa o limite medial do defeito nesta localização?",
                          "opts":  [
                                       "Linha semilunar (borda medial do músculo reto abdominal)",
                                       "Borda lateral do músculo reto abdominal",
                                       "Ligamento falciforme",
                                       "Linha mediana (linea alba)"
                                   ],
                          "c":  0,
                          "exp":  "Hérnia de Spiegel ocorre através da fascia de Spigelius (borda lateral do reto abdominal/linha semilunar); este é o limite medial do defeito, geralmente abaixo da linha arqueada de Douglas."
                      },
                      {
                          "q":  "Homem 55 anos com antecedente de hérnia inguinal bilateral primária. Deseja tratamento definitivo. Qual é a vantagem técnica mais relevante da herniorrafia inguinal bilateral simultânea por via laparoscópica em comparação com Lichtenstein bilateral?",
                          "opts":  [
                                       "Menor taxa de recorrência comprovada em longo prazo versus Lichtenstein",
                                       "Visualização direta de ambas hérnias com avaliação de parede anterior única e redução de morbidade parietal",
                                       "Eliminação completa de risco de infecção de prótese",
                                       "Menor custo operatório total e maior rapidez de retorno ao trabalho"
                                   ],
                          "c":  1,
                          "exp":  "Laparoscopia bilateral permite acesso único à parede peritoneal com visualização simultânea de ambos lados, evitando duas incisões e dissecções separadas; reduz morbidade parietal comparado a dois acessos Lichtenstein."
                      },
                      {
                          "q":  "Paciente 42 anos apresenta hérnia em região medial à linha semilunar, mas ACIMA da linha arqueada de Douglas, com diagnóstico diferencial entre hérnia de Spiegel e hérnia inguinal direta alta. Qual achado clínico-anatômico melhor diferencia Spiegel de inguinal direta?",
                          "opts":  [
                                       "Posição do defeito anterior à fascia de Camper: Spiegel é subfascial entre reto e oblíquo interno",
                                       "Presença de impulso ao Valsalva menos evidente em Spiegel que em inguinal",
                                       "Redutibilidade reduzida em Spiegel devido ao encarceramento frequente",
                                       "Localização em relação ao ligamento inguinal: Spiegel está sempre acima dele"
                                   ],
                          "c":  0,
                          "exp":  "Hérnia de Spiegel forma-se entre músculos reto abdominal e oblíquo interno (subfascial), conferindo localização profunda às vezes imperceptível clinicamente; inguinal direta é superficial na parede anterior do canal inguinal."
                      },
                      {
                          "q":  "Homem 68 anos com queixa de dor em coxa medial associada a sensação de compressão, sem tumoração palpável evidente. Ressonância magnética sugere conteúdo através do foramen obturado. Qual é o desafio diagnóstico mais importante da hérnia obturatória?",
                          "opts":  [
                                       "Ausência de tumoração palpável por localização profunda intrapélvica, retardando diagnóstico",
                                       "Confusão com hérnia de Spiegel por localização lateral semelhante",
                                       "Elevada taxa de recorrência que inviabiliza tratamento conservador",
                                       "Simulação de hérnia femoral lateral com erro na localização do defeito"
                                   ],
                          "c":  0,
                          "exp":  "Hérnia obturatória passa pelo foramen obturado (estrutura profunda/intrapélvica), conferindo sinal clínico escasso e ausência de massa superficial; frequentemente diagnosticada tardiamente quando estrangulada ou em exames de imagem."
                      },
                      {
                          "q":  "Homem de 45 anos apresenta abaulamento inguinal direito indolor, redutível, sem história de trauma. Ao exame, o dedo introduzido no canal inguinal toca a parede posterior sem ultrapassá-la. Qual é o tipo de hérnia inguinal?",
                          "opts":  [
                                       "Hérnia inguinal indireta com saco herniário patente",
                                       "Hérnia de Spiegel com localização acima da linha arqueada",
                                       "Hérnia femoral com trajeto medial à artéria femoral",
                                       "Hérnia inguinal direta por enfraquecimento do assoalho inguinal"
                                   ],
                          "c":  3,
                          "exp":  "Hérnia direta protrai através do triângulo de Hasselbach (músculos oblíquos enfraquecidos), localiza-se medial ao epidídimo e toca a parede posterior do canal sem transpô-la."
                      },
                      {
                          "q":  "Mulher de 52 anos com abaulamento em região medial da raiz da coxa, irredutível, com dor intensa. Ao exame, a lesão está localizada medial e profunda à veia femoral. Qual é o diagnóstico e a melhor conduta?",
                          "opts":  [
                                       "Hérnia femoral encarcerada; correção emergencial via abordagem baixa de Lockwood",
                                       "Hérnia inguinal indireta; reparo laparoscópico por não ser femoral",
                                       "Hérnia femoral estrangulada; reparo eletivo em 30 dias com malha",
                                       "Lipoma inguinal; observação com anti-inflamatório e repouso"
                                   ],
                          "c":  0,
                          "exp":  "Localização medial à veia femoral caracteriza hérnia femoral. Sintomas de encarceramento (irredutibilidade, dor) exigem correção emergencial via abordagem baixa (Lockwood) ou alta (Rutkow)."
                      },
                      {
                          "q":  "Lactente de 8 meses com abaulamento umbilical redutível desde o nascimento. Pai relata que a mãe foi orientada a aguardar. Aos 8 meses, a hérnia persiste sem complicações. Qual é a conduta mais apropriada segundo o padrão brasileiro?",
                          "opts":  [
                                       "Repouso e enfaixamento abdominal até fechamento espontâneo",
                                       "Correção cirúrgica imediata por risco de estrangulamento",
                                       "Observação até 4-5 anos de idade; considerar cirurgia se persistir ou aumentar",
                                       "Colocação de faixa elástica para compressão contínua"
                                   ],
                          "c":  2,
                          "exp":  "Hérnia umbilical pediátrica tem alta taxa de fechamento espontâneo até 4-5 anos. Conduta expectante é adequada sem complicações; cirurgia indicada se persistência além dessa idade ou encarceramento."
                      },
                      {
                          "q":  "Paciente de 38 anos submetido a herniorrafia inguinal com técnica de Lichtenstein apresenta recidiva após 2 anos. Qual é o fator técnico mais frequentemente associado a insucesso nessa técnica?",
                          "opts":  [
                                       "Uso de fio não-absorvível inadequado para o fechamento do assoalho",
                                       "Omissão do bloqueio do nervo iliohipogástrico antes da malha",
                                       "Sutura inadequada da malha na borda medial ou falta de sobreposição dos componentes",
                                       "Fixação inadequada da malha ao ligamento de Cooper"
                                   ],
                          "c":  2,
                          "exp":  "Lichtenstein é técnica de tensão-livre sobre o assoalho. Falha técnica mais comum é sutura inadequada da malha (borda medial, inadequada sobreposição), permitindo deslocamento e recidiva."
                      },
                      {
                          "q":  "Mulher de 55 anos com hérnia incisional sintomática 18 meses após cesariana. A lesão mede 5 cm, é redutível e sem sinais de encarceramento. Qual é a melhor abordagem cirúrgica?",
                          "opts":  [
                                       "Reconstrução com enxerto de fascia lata autógena",
                                       "Reparo retrorretual (Rives-Stoppa) com malha não-absorvível",
                                       "Herniorrafia com aposição de fáscia aponeurótica sem malha",
                                       "Herniorrafia primária com fechamento simples em massa"
                                   ],
                          "c":  1,
                          "exp":  "Hérnia incisional em mulher com cesariana prévia indica debilidade fascial. Reparo retrorretual (Rives-Stoppa) com malha oferece menor recidiva (1-5%) e reforço adequado versus herniorrafia primária."
                      },
                      {
                          "q":  "Paciente de 62 anos com hérnia inguinal esquerdaindireta volumosa (Nyhus IIIB) deseja reparo bilateral simultâneo. Qual é a vantagem da abordagem laparoscópica total (TEP ou TAPP) em relação à abordagem aberta?",
                          "opts":  [
                                       "Acesso único para reparo bilateral com visão panorâmica; menor morbidade parietal",
                                       "Evita completamente a necessidade de malha sintética",
                                       "Menor custo operatório e dispensa de anestesia geral",
                                       "Melhor controle de recidiva; só essa técnica permite fixação ao ligamento de Cooper"
                                   ],
                          "c":  0,
                          "exp":  "TEP/TAPP permite acesso único (um portal para bilateral) com visão panorâmica do espaço pré-peritoneal. Reparo bilateral com menor trauma parietal, menor dor pós-operatória que duas incisões abertas."
                      },
                      {
                          "q":  "Homem de 48 anos apresenta hérnia de Spiegel dolorosa, diagnosticada por ultrassom. Durante exame físico, a lesão situa-se na linha de Spiegel. Qual é a particularidade anatômica que dificulta o diagnóstico clínico dessa hérnia?",
                          "opts":  [
                                       "Sempre acompanhada de síndrome de Síndrome Préperitoneal",
                                       "Está sempre localizada abaixo da linha arqueada de Douglas",
                                       "Protrai através da fáscia de Camper, mas permanece sob a bainha do músculo oblíquo externo",
                                       "Localiza-se medial ao músculo reto abdominal, impossibilitando palpação externa"
                                   ],
                          "c":  2,
                          "exp":  "Hérnia de Spiegel protrai pela linha de Spiegel, porém permanece contida pela fáscia do oblíquo externo. Essa cobertura aponeurótica oculta a lesão ao exame, dificultando diagnóstico clínico; ultrassom/TC são fundamentais."
                      },
                      {
                          "q":  "Paciente de 70 anos com hérnia inguinal estrangulada direita apresenta-se com dor súbita, abaulamento tenso e irreducível, náuseas. Qual é o primeiro passo na conduta?",
                          "opts":  [
                                       "Avaliação clínica completa, reposição volêmica IV, antibióticos e preparo para cirurgia emergencial",
                                       "Tentativa de redução manual sob analgesia para aliviar sintomas",
                                       "Ultrassom doppler para confirmar viabilidade do conteúdo herniário antes de qualquer intervenção",
                                       "Observação de 4-6 horas com analgesia para documentar se desencarcera espontaneamente"
                                   ],
                          "c":  0,
                          "exp":  "Estrangulamento herniário é emergência cirúrgica. Manejo inicial: avaliação clínica, reposição volêmica IV, antibióticos de largo espectro e preparo emergencial para cirurgia. Redução manual é contraindicada (risco de redução em bloco)."
                      },
                      {
                          "q":  "Cirurgião realiza herniorrafia inguinal bilateral aberta em paciente de 55 anos. Na técnica de Bassini, qual é o componente crítico que diferencia dessa técnica em relação à de Lichtenstein?",
                          "opts":  [
                                       "Bassini é técnica única para hérnias femorais, não aplicável a inguinais",
                                       "Bassini reposiciona o músculo cremaster e fecha o assoalho inguinal com sutura de tensão",
                                       "Bassini não requer incisão inguinal; é realizada por laparoscopia",
                                       "Bassini utiliza apenas fio absorvível, enquanto Lichtenstein usa malha sintética"
                                   ],
                          "c":  1,
                          "exp":  "Bassini é técnica clássica com fechamento do assoalho inguinal por sutura de tensão (fáscia transversa aproximada). Diferencia de Lichtenstein (tensão-livre com malha) porque cria tensão significativa nas suturas, maior recidiva e dor pós-operatória."
                      },
                      {
                          "q":  "Homem de 58 anos com hérnia incisional volumosa após laparotomia exploratória 5 anos antes apresenta manutenção de conteúdo visceral herniado, disfunção parietal abdominal e sintomas compressivos. Qual é a melhor indicação para cirurgia além da sintomatologia?",
                          "opts":  [
                                       "Redução de custos com fármacos anti-inflamatórios para manejo conservador",
                                       "Restauração da continuidade fascial para evitar piora progressiva e complicações a longo prazo",
                                       "Prevenção de estrangulamento, que é comum em hérnias incisionais volumosas",
                                       "Prevenção de infecção secundária por contaminação cutânea externa"
                                   ],
                          "c":  1,
                          "exp":  "Hérnia incisional grande com disfunção parietal progressiva tem risco crescente de complicações. Restauração fascial via reparo com malha previne piora progressiva, melhora função abdominal e reduz risco futuro de encarceramento/estrangulamento."
                      },
                      {
                          "q":  "Homem de 52 anos com hérnia inguinal esquerda irredutível há 6 horas, apresentando dor intensa, náusea e ausência de ruídos hidroaéreos. À palpação, massa endurecida e dolorosa. Qual complicação está presente e qual a conduta imediata?",
                          "opts":  [
                                       "Hérnia direta; herniorrafia eletiva em 2 semanas",
                                       "Incisionalismo; antibióticos e repouso",
                                       "Encarceramento; observação clínica com analgesia e redução manual",
                                       "Estrangulamento; reparo urgente após estabilização clínica"
                                   ],
                          "c":  3,
                          "exp":  "Sinais vitais alterados, dor severa e ausência de peristaltismo indicam estrangulamento com isquemia tecidual, exigindo reparo urgente após ressuscitação."
                      },
                      {
                          "q":  "Mulher de 68 anos com hérnia femoral à direita, assintomática, descoberta ao exame físico de rotina. Qual é a localização anatômica correta dessa hérnia em relação aos componentes do trígono femoral?",
                          "opts":  [
                                       "Medial à artéria femoral, entre ligamento inguinal e Cooper",
                                       "Posterior ao ligamento inguinal, no canal addutor",
                                       "Medial à veia femoral, através do septo femoral",
                                       "Lateral à artéria femoral, anterior à fáscia pectínea"
                                   ],
                          "c":  0,
                          "exp":  "Hérnia femoral passa medial à veia femoral (canal femoral), entre ligamento inguinal superiormente e ligamento Cooper inferiormente."
                      },
                      {
                          "q":  "Homem de 45 anos submetido a herniorrafia inguinal bilateral por técnica de Lichtenstein. Qual material sintético foi utilizado e qual a taxa esperada de recidiva em 5 anos com essa técnica?",
                          "opts":  [
                                       "Poliglactina; 8-10%",
                                       "Nylon absorvível; 15-20%",
                                       "Polipropileno; 3-5%",
                                       "Politetrafluoretileno; 2-3%"
                                   ],
                          "c":  2,
                          "exp":  "Lichtenstein utiliza tela de polipropileno em tensão-livre, com recidiva de 3-5% em 5 anos, padrão-ouro para hérnia inguinal primária."
                      },
                      {
                          "q":  "Criança de 3 anos com hérnia umbilical de 2,5 cm de diâmetro, assintomática, sem história de encarceramento. Qual é a conduta mais apropriada segundo consenso pediátrico?",
                          "opts":  [
                                       "Uso de fita adesiva elástica com revisões trimestrais",
                                       "Reparo cirúrgico imediato para evitar complicações",
                                       "Injeção de substância esclerosante intradérmica",
                                       "Observação clínica; reparo eletivo se persistir após 4-5 anos"
                                   ],
                          "c":  3,
                          "exp":  "Hernias umbilicais pequenas fecham espontaneamente em 80-90% até 4-5 anos em crianças. Reparo eletivo apenas se sintomática ou persistir."
                      },
                      {
                          "q":  "Mulher de 55 anos com hérnia incisional ventral após cesárea há 20 anos, com 8 cm de defeito. Qual fator de risco cirúrgico foi provavelmente importante nessa recidiva tardia?",
                          "opts":  [
                                       "Sutura com fio monofilamentar absorvível",
                                       "Infecção de ferida operatória imediata (até 30 dias)",
                                       "Obesidade, tosse crônica ou esforço físico repetido",
                                       "Anestesia geral prolongada durante parto"
                                   ],
                          "c":  2,
                          "exp":  "Recidiva tardia (\u003e5 anos) associa-se a fatores biomecânicos: obesidade, tosse, esforço; não a complicações cirúrgicas agudas."
                      },
                      {
                          "q":  "Homem de 62 anos com hérnia de Spiegel à esquerda, palpável logo medial à borda lateral do músculo reto abdominal, acima da linha arqueada. Qual nervo está em risco durante o reparo desta hérnia?",
                          "opts":  [
                                       "Nervos ilio-hipogástrico e ilioinguinal",
                                       "Nervo obturatório (L3-L4)",
                                       "Ramo cutâneo femoral lateral",
                                       "Nervo pudendo (S2-S4)"
                                   ],
                          "c":  0,
                          "exp":  "Nervo ilio-hipogástrico e ilioinguinal passam pela fascia de Camper próximo ao defeito de Spiegel, risco de lesão durante dissecção."
                      },
                      {
                          "q":  "Homem de 58 anos com hérnia inguinal esquerda primária, sem fatores de risco para recidiva. Comparando-se técnica aberta (Lichtenstein) com laparoscópica (TEP), qual vantagem significativa a abordagem laparoscópica oferece?",
                          "opts":  [
                                       "Reparo bilateral simultâneo com menor morbidade",
                                       "Possibilidade de reparo sem tela sintética",
                                       "Menor taxa de recidiva em longo prazo",
                                       "Menor custo hospitalar e anestésico"
                                   ],
                          "c":  0,
                          "exp":  "TEP permite reparo bilateral simultâneo com mesma incisão, reduzindo tempo total e morbidade comparado a dois acessos abertos."
                      },
                      {
                          "q":  "Mulher de 70 anos com hérnia femoral à direita, assintomática, 1,5 cm. Qual é a conduta recomendada baseado no risco de encarceramento dessa localização herniária?",
                          "opts":  [
                                       "Observação clínica; reparo apenas se sintomática",
                                       "Reparo eletivo, pois risco de encarceramento é alto (20-40%)",
                                       "Compressão externa com uso de bragueiro herniário",
                                       "Infiltração com solução esclerosante periódica"
                                   ],
                          "c":  1,
                          "exp":  "Hérnia femoral tem alto risco de encarceramento (20-40%), mesmo assintomática; reparo eletivo é recomendado para evitar emergência."
                      },
                      {
                          "q":  "Homem de 48 anos com hérnia inguinal indireta à direita, classificada como Nyhus tipo II. Qual estrutura anatômica está preservada e qual está comprometida nesta classificação?",
                          "opts":  [
                                       "Ligamento de Cooper preservado; parede medial do canal enfraquecida",
                                       "Piso do canal inguinal preservado; ligamento de Cooper comprometido",
                                       "Fáscia transversalis íntegra; todos os limites herniários dilatados",
                                       "Anéis inguinais profundo e superficial patentes; ligamento de Cooper intacto"
                                   ],
                          "c":  0,
                          "exp":  "Nyhus tipo II (indireta-móvel) mantém ligamento Cooper e piso integros, mas com enfraquecimento progressivo da parede medial."
                      },
                      {
                          "q":  "Mulher de 64 anos submetida a herniorrafia inguinal esquerda por técnica de Bassini há 8 anos. Ela retorna com recidiva ipsilateral. Qual limitação técnica da Bassini predispõe a essa complicação comparada à Lichtenstein?",
                          "opts":  [
                                       "Transecção inadvertida do ligamento inguinal superficial",
                                       "Incisão muito proximal afastando do defeito herniário",
                                       "Uso de tela não absorvível de qualidade inferior",
                                       "Reparo em tensão, sem reforço com prótese"
                                   ],
                          "c":  3,
                          "exp":  "Bassini realiza sutura anatômica de estruturas sem tela (tensão-dependente); recidiva 10-15%, superior a Lichtenstein (3-5%) tensão-livre."
                      },
                      {
                          "q":  "Paciente de 58 anos com hérnia inguinal esquerda irredutível há 6 horas, dor progressiva, náuseas e ausência de eliminação de gases nas últimas 4 horas. Ao exame, massa inguinal tenra, edemaciada, com sinais de irritação peritoneal. Qual achado intraoperatório indicaria conversão para laparotomia e ressecção de alça?",
                          "opts":  [
                                       "Alça com coloração negra, ausência de brilho seroso e sem resposta à estimulação",
                                       "Alça com edema moderado, palidez relativa mas com pulso vascular palpável ao doppler",
                                       "Alça com cor arroxeada, ausência de peristaltismo visível mas com perfusão capilar preservada",
                                       "Alça com congestão venosa, espessura aumentada mas com reflexo mucoso presente"
                                   ],
                          "c":  0,
                          "exp":  "Necrose irreversível caracteriza-se por coloração negra, perda de brilho seroso (indicativo de peritonite), ausência de viabilidade. Ressecção mandatória para evitar sepse."
                      },
                      {
                          "q":  "Homem de 65 anos com hérnia inguinal bilateral (direita pequena, esquerda volumosa com sintomatologia). Apresenta comorbidades (DPOC, insuficiência cardíaca NYHA II). Qual estratégia cirúrgica seria mais apropriada segundo evidências atuais?",
                          "opts":  [
                                       "Repair de Lichtenstein unilateral (lado sintomático) sob anestesia local; contralateral em segundo tempo se necessário",
                                       "Repair bilateral de Lichtenstein sob anestesia regional bloqueio do plexo inguinal",
                                       "Observação clínica de ambas; cirurgia somente se houver sintomas bilaterais",
                                       "Repair laparoscópica bilateral em único tempo sob anestesia geral com intubação orotraqueal"
                                   ],
                          "c":  0,
                          "exp":  "Lichtenstein unilateral sob anestesia local minimiza complicações cardiopulmonares em paciente de risco. Abordagem contralateral posterior se sintomática reduz morbidade perioperatória comparado a bilateral único tempo."
                      },
                      {
                          "q":  "Mulher de 42 anos com histórico de cesárea há 8 anos apresenta hérnia incisional ventral (10×8 cm) com episódios recorrentes de encarceramento parcial. Tomografia mostra defeito fascial amplo com conteúdo intestinal e gordura omental. Qual técnica ofereceria menor taxa de recidiva considerando o padrão de falha?",
                          "opts":  [
                                       "Herniorrafia com colocação de tela em posição retrorretusa (Rives-Stoppa) associada à plicatura aponeurótica",
                                       "Repair puramente laparoscópica com tela intraperitoneal sem reforço facial",
                                       "Fechamento primário simples com sutura irreabsorvível em plano único",
                                       "Enxerto de tecido biológico dermis sem fixação com pontos"
                                   ],
                          "c":  0,
                          "exp":  "Defeito amplo recorrente requer reforço com tela em posição retrorretusa (vascularização superior) + plicatura fascial restabelece anatomia. Taxa recidiva \u003c10% versus primário simples (\u003e30%)."
                      },
                      {
                          "q":  "Homem de 72 anos procura avaliação para hérnia inguinal direta pequena (assintomática, detectada incidentalmente em ultrassom). Antecedente de infarto miocárdio há 2 anos, em uso de anticoagulante para fibrilação atrial. Qual conduta está embasada nas diretrizes atuais para este cenário?",
                          "opts":  [
                                       "Observação clínica com orientações sobre sinais de alerta; cirurgia apenas se houver sintomatologia ou mudança de características",
                                       "Anticoagulação deve ser suspensa 7 dias antes para realizar reparo sob anestesia geral",
                                       "Reparo eletivo imediato sob anestesia regional para evitar futura emergência",
                                       "Reparo urgente laparoscópico bilateral profilático para reduzir risco de complicações futuras"
                                   ],
                          "c":  0,
                          "exp":  "Hérnia inguinal direta assintomática em idoso com comorbidades cardíacas requer observação; reparo eletivo somente se sintomas ou evidência de risco (encarceramento). Risco operatório supera benefício em assintomático."
                      },
                      {
                          "q":  "Mulher de 55 anos apresenta massa inguinal indolor, progressiva há 3 meses sem déficit motor. Exame: tumefação na região medial ao vaso femoral, abaixo do ligamento inguinal. Ao repouso, é reputável. Qual diagnóstico está mais consistente com achados clínico-anatômicos e qual abordagem cirúrgica seria indicada?",
                          "opts":  [
                                       "Aneurisma da artéria femoral; ultrassom com doppler e encaminhamento a cirurgia vascular",
                                       "Hérnia inguinal direta; reparo de Lichtenstein com tela suprafascial",
                                       "Linfonodomegalia inguinal; necessário investigação oncológica antes de intervenção",
                                       "Hérnia femoral; abordagem de Lockwood (infra-inguinal) com tela pré-peritoneal"
                                   ],
                          "c":  3,
                          "exp":  "Hérnia femoral: massa abaixo ligamento inguinal, medial à artéria femoral (canal femoral). Abordagem de Lockwood infra-inguinal permite dissecção segura com tela pré-peritoneal ou suprafascial."
                      },
                      {
                          "q":  "Homem 58 anos com hérnia inguinal esquerda volumosa, irredutível há 3 dias, dor progressiva, náuseas e vômitos. Ao exame: abaulamento inguinal tenso, doloroso, sem sinais peritoniais. Tomografia evidencia alça delgada dilatada no canal inguinal. Qual é a conduta mais apropriada considerando o risco de lesão iatrógena?",
                          "opts":  [
                                       "Redução manual progressiva com analgesia seguida de herniorrafia eletiva em 6-8 semanas",
                                       "Observação clínica com antibióticos e dieta zero por 48-72 horas antes de cirurgia",
                                       "Herniorrafia de Lichtenstein em urgência sob anestesia local",
                                       "Herniorrafia aberta (Lichtenstein) com ressecção intestinal se viável, sob anestesia geral"
                                   ],
                          "c":  3,
                          "exp":  "Hérnia estrangulada requer herniorrafia urgente com anestesia geral para permitir avaliação intestinal adequada e ressecção se necrose; Lichtenstein viável se viabilidade confirmada, evitando lesão em urgência."
                      },
                      {
                          "q":  "Mulher 45 anos, hérnia incisional após cirurgia bariátrica há 2 anos, defeito de 8 cm sem sintomas, índice de massa corporal 32 kg/m². Na avaliação pré-operatória para herniorrafia, qual fator anatômico e técnico determina o uso de tela de reforço retromuscular versus suprafascial em Lichtenstein?",
                          "opts":  [
                                       "Posição suprafascial é sempre preferida em mulheres com cicatrizes prévias",
                                       "Presença de cicatriz anterior e força de parede comprometida indicam reforço retromuscular",
                                       "Tamanho do defeito \u003e 6 cm requer obrigatoriamente tela retromuscular",
                                       "Tela suprafascial reduz custo e oferece menor taxa de recidiva independente de tamanho"
                                   ],
                          "c":  1,
                          "exp":  "Tela retromuscular oferece vascularização superior, cobertura muscular e menor contato visceral; indicada em defeitos maiores e cicatrizes prévias com parede comprometida."
                      },
                      {
                          "q":  "Homem 72 anos com hérnia femoral direita de 3 cm, assintomática, descoberta incidentalmente. Antecedente de acidente vascular cerebral com sequela funcional leve. Qual é a recomendação baseada no risco de estrangulamento e morbidade operatória?",
                          "opts":  [
                                       "Conduta expectante com seguimento clínico trimestral devido ao alto risco operatório",
                                       "Herniografia de ressonância para melhor delimitação antes de decisão terapêutica",
                                       "Herniorrafia eletiva imediata; hérnia femoral tem risco de estrangulamento até 50% mesmo pequena",
                                       "Herniorrafia apenas se sintomática ou se defeito \u003e 5 cm em ultrassom"
                                   ],
                          "c":  2,
                          "exp":  "Hérnia femoral assintomática tem risco de estrangulamento até 40-50%; mesmo pequenas. Herniorrafia eletiva é indicada em paciente operável, evitando urgência futura com comorbidades."
                      },
                      {
                          "q":  "Menino 3 anos com hérnia umbilical de 1,5 cm, mãe preocupada com encarceramento. Exame: redutível, sem irritação de pele, desenvolvimento normal. Qual é a integração adequada de conhecimento fisiopatológico e conduta?",
                          "opts":  [
                                       "Herniorrafia eletiva imediata para evitar encarceramento; risco é 1-2% ao ano",
                                       "Usar fita adesiva compressiva para acelerar fechamento; cirurgia se não fechar até 6 anos",
                                       "Obrigação cirúrgica antes dos 4 anos; após essa idade o risco de encarceramento aumenta exponencialmente",
                                       "Expectativa até 4-5 anos pois 80-90% fecham espontaneamente; cirurgia se persistir ou se encarcerada"
                                   ],
                          "c":  3,
                          "exp":  "História natural da hérnia umbilical em crianças: 80-90% fecham espontaneamente até 4-5 anos. Risco encarceramento é baixo. Cirurgia indicada se persistir após 4-5 anos ou se encarcerada."
                      },
                      {
                          "q":  "Mulher 62 anos com hérnia de Spiegel direita de 6 cm com queixa de dor intermitente. Ressonância confirma defeito entre músculo semilunar e linha semilunar, com conteúdo de epíploon. Considerando anatomia e técnica, qual abordagem oferece menor morbidade e melhor visualização?",
                          "opts":  [
                                       "Abordagem laparoscópica com tela retromuscular (RIVES); visualização de espaço retromuscular e menor dor pós-operatória",
                                       "Abordagem anterior transversa; evita violação do fascia posterior e preserva inervação",
                                       "Incisão reta anterior clássica; permite redução segura e herniorrafia primária",
                                       "Herniorrafia robótica para máxima precisão dado o tamanho do defeito"
                                   ],
                          "c":  0,
                          "exp":  "Abordagem laparoscópica com tela retromuscular (técnica RIVES) oferece visualização superior do espaço retromuscular, menor trauma parietal, menor dor pós-op e taxas de recidiva comparáveis à aberta."
                      }
                  ]
}